{
    "Lunedì": {
        "ora_1": [
            "SACCHETTI",
            "VARONE"
        ],
        "ora_2": [
            "MARCOCCIA"
        ],
        "ora_3": [
            "SCHIAVI"
        ],
        "ora_4": [
            "MASSA",
            "ATTI"
        ],
        "ora_5": [
            "MASSA",
            "ATTI"
        ],
        "ora_6": [
            "ATTI"
        ]
    },
    "Martedì": {
        "ora_1": [
            "MASSA",
            "CIPRIANI"
        ],
        "ora_2": [
            "MASSA",
            "CIPRIANI"
        ],
        "ora_3": [
            "NICOLIA",
            "VARONE"
        ],
        "ora_4": [
            "NICOLIA",
            "VARONE"
        ],
        "ora_5": [
            "MARCOCCIA"
        ],
        "ora_6": [
            "SACCHETTI"
        ]
    },
    "Mercoledì": {
        "ora_1": [
            "SCHIAVI"
        ],
        "ora_2": [
            "BRESSAN"
        ],
        "ora_3": [
            "BRAGALONE"
        ],
        "ora_4": [
            "ATTI"
        ],
        "ora_5": [
            "MAURO"
        ],
        "ora_6": [
            "MARCOCCIA"
        ]
    },
    "Giovedì": {
        "ora_1": [
            "VARONE"
        ],
        "ora_2": [
            "SACCHETTI"
        ],
        "ora_3": [
            "SACCHETTI"
        ],
        "ora_4": [
            "MASSA",
            "CIPRIANI"
        ],
        "ora_5": [
            "CIPRIANI",
            "SCHIAVI"
        ],
        "ora_6": [
            "CIPRIANI"
        ]
    },
    "Venerdì": {
        "ora_1": [
            "ATTI"
        ],
        "ora_2": [
            "MARCOCCIA"
        ],
        "ora_3": [
            "SACCHETTI"
        ],
        "ora_4": [
            "SACCHETTI"
        ],
        "ora_5": [
            "NICOLIA",
            "CIPRIANI"
        ],
        "ora_6": [
            "NICOLIA",
            "CIPRIANI"
        ]
    }
}
